datashadric/__init__.py
datashadric/aiagents.py
datashadric/dataframing.py
datashadric/mlearning.py
datashadric/plotters.py
datashadric/regression.py
datashadric/stochastics.py
datashadric-0.2.3.dist-info/licenses/LICENSE
datashadric-0.2.3.dist-info/METADATA
datashadric-0.2.3.dist-info/WHEEL
datashadric-0.2.3.dist-info/top_level.txt
datashadric-0.2.3.dist-info/RECORD
