Metadata-Version: 2.4
Name: datashadric
Version: 0.2.3
Summary: An exploratory data science toolkit for analysis, machine learning, multimodal ai agents for text and image processing, and visualization (Apache Superset)
Author-email: "Paul Namalomba (GitHub: paulnamalomba)" <kabwenzenamalomba@gmail.com>
Maintainer-email: "Paul Namalomba (GitHub: paulnamalomba)" <kabwenzenamalomba@gmail.com>
License: MIT License
Project-URL: Homepage, https://github.com/paulnamalomba/datashadric
Project-URL: Bug Reports, https://github.com/paulnamalomba/datashadric/issues
Project-URL: Source, https://github.com/paulnamalomba/datashadric/src/datashadric
Project-URL: Documentation, https://github.com/paulnamalomba/datashadric/README.md
Keywords: data science,machine learning,statistics,visualization,pandas,analysis
Classifier: Development Status :: 3 - Alpha
Classifier: Intended Audience :: Science/Research
Classifier: Intended Audience :: Developers
Classifier: License :: OSI Approved :: MIT License
Classifier: Operating System :: OS Independent
Classifier: Programming Language :: Python :: 3
Classifier: Programming Language :: Python :: 3.8
Classifier: Programming Language :: Python :: 3.9
Classifier: Programming Language :: Python :: 3.10
Classifier: Programming Language :: Python :: 3.11
Classifier: Programming Language :: Python :: 3.12
Classifier: Programming Language :: Python :: 3.13
Classifier: Topic :: Scientific/Engineering :: Information Analysis
Classifier: Topic :: Software Development :: Libraries :: Python Modules
Requires-Python: >=3.8
License-File: LICENSE
Requires-Dist: pandas
Requires-Dist: cmake
Requires-Dist: numpy
Requires-Dist: scikit-learn
Requires-Dist: matplotlib
Requires-Dist: seaborn
Requires-Dist: scipy
Requires-Dist: statsmodels
Requires-Dist: plotly
Requires-Dist: google-generativeai
Provides-Extra: dev
Requires-Dist: pytest>=6.0; extra == "dev"
Requires-Dist: pytest-cov>=2.0; extra == "dev"
Requires-Dist: black>=21.0; extra == "dev"
Requires-Dist: flake8>=3.8; extra == "dev"
Requires-Dist: mypy>=0.900; extra == "dev"
Provides-Extra: viz
Requires-Dist: apache-superset>=5.0.0; extra == "viz"
Requires-Dist: pyarrow>=15.0.0; extra == "viz"
Provides-Extra: docs
Requires-Dist: sphinx>=4.0; extra == "docs"
Requires-Dist: sphinx-rtd-theme>=1.0; extra == "docs"
Dynamic: license-file
